README.rst
setup.py
sphinxcontrib/__init__.py
sphinxcontrib/imgur/__init__.py
sphinxcontrib/imgur/cache.py
sphinxcontrib/imgur/directives.py
sphinxcontrib/imgur/imgur_api.py
sphinxcontrib/imgur/nodes.py
sphinxcontrib/imgur/roles.py
sphinxcontrib/imgur/sphinx_api.py
sphinxcontrib_imgur.egg-info/PKG-INFO
sphinxcontrib_imgur.egg-info/SOURCES.txt
sphinxcontrib_imgur.egg-info/dependency_links.txt
sphinxcontrib_imgur.egg-info/requires.txt
sphinxcontrib_imgur.egg-info/top_level.txt
sphinxcontrib_imgur.egg-info/zip-safe