Metadata-Version: 1.1
Name: sphinxcontrib-imgur
Version: 2.0.1
Summary: Sphinx extension that embeds Imgur images, albums, and their metadata in documents.
Home-page: https://github.com/Robpol86/sphinxcontrib-imgur
Author: @Robpol86
Author-email: robpol86@gmail.com
License: MIT
Keywords: sphinx imgur
Platform: UNKNOWN
Classifier: Development Status :: 5 - Production/Stable
Classifier: Environment :: MacOS X
Classifier: Environment :: Plugins
Classifier: Environment :: Win32 (MS Windows)
Classifier: Framework :: Sphinx :: Extension
Classifier: Intended Audience :: Developers
Classifier: License :: OSI Approved :: MIT License
Classifier: Operating System :: MacOS :: MacOS X
Classifier: Operating System :: Microsoft :: Windows
Classifier: Operating System :: POSIX :: Linux
Classifier: Operating System :: POSIX
Classifier: Programming Language :: Python :: 2.7
Classifier: Programming Language :: Python :: 3.3
Classifier: Programming Language :: Python :: 3.4
Classifier: Programming Language :: Python :: Implementation :: PyPy
Classifier: Topic :: Documentation :: Sphinx
Classifier: Topic :: Software Development :: Documentation
